{
  "run_date": "2026-04-20",
  "label": "April 20, 2026",
  "generated_on": "2026-04-17",
  "total_leads": 21,
  "high_priority": 4,
  "medium_priority": 16,
  "low_supplemental": 1,
  "discovery_channels": [
    "CLMP Independent Press Directory",
    "Reedsy Independent Publishers Directory",
    "Poets & Writers Small Presses DB",
    "IBPA Member Directory",
    "LinkedIn Business Author Network",
    "Substack / Creator Economy Discovery",
    "Kickstarter Publishing Discovery",
    "Instagram / Food Creator Discovery"
  ],
  "deduplication_checked_against": [
    "2026-03-26",
    "2026-03-27",
    "2026-03-30",
    "2026-03-31",
    "2026-04-06",
    "2026-04-13"
  ],
  "leads": [
    {
      "id": 1,
      "score": 9,
      "priority": "high",
      "category": "Hybrid Publisher / Author Services",
      "name": "Rootstock Publishing",
      "source": "IBPA Member Directory",
      "email": "samantha@rootstockpublishing.com",
      "phone": "(802) 477-3131",
      "website": "https://rootstockpublishing.com",
      "location": "Montpelier, VT",
      "notes": "Vermont-based hybrid press founded 2014, 10-15 titles annually, Ingram distribution. Recurring multi-title print opportunity. Single-contact model directly serves hybrid publisher's author-promise requirements."
    },
    {
      "id": 2,
      "score": 8,
      "priority": "high",
      "category": "Business & Authority Author",
      "name": "Paul Millerd",
      "source": "LinkedIn Business Author Network",
      "email": "paul@pathlesspath.com",
      "phone": "",
      "website": "https://pathlesspath.com",
      "location": "New York, NY",
      "notes": "Self-published author of 'The Pathless Path' (30,000+ copies sold), 30,000+ Substack subscribers, second book in development 2026. Offset pricing at 500+ copies improves per-unit economics vs KDP."
    },
    {
      "id": 3,
      "score": 8,
      "priority": "high",
      "category": "Small Press (6-20 titles/yr)",
      "name": "Tortoise Books",
      "source": "CLMP Independent Press Directory",
      "email": "editors@tortoisebooks.com",
      "phone": "",
      "website": "https://tortoisebooks.com",
      "location": "Chicago, IL",
      "notes": "Chicago-based literary press, 6-10 titles annually, 3.5 hours from Ann Arbor. Midwest peer with national distribution and growing critical reputation."
    },
    {
      "id": 4,
      "score": 8,
      "priority": "high",
      "category": "Solo Author - Print-Ready",
      "name": "Joanna Penn (The Creative Penn)",
      "source": "Substack / Creator Economy Discovery",
      "email": "joanna@thecreativepenn.com",
      "phone": "",
      "website": "https://thecreativepenn.com",
      "location": "London, UK (61% US audience)",
      "notes": "40+ published titles, 100,000+ followers, 2026 shift to premium US-printed physical editions announced. Existing US wholesale distribution sized for 1,000+ copy offset runs."
    },
    {
      "id": 5,
      "score": 7,
      "priority": "medium",
      "category": "Hybrid Publisher / Author Services",
      "name": "She Writes Press",
      "source": "Reedsy Independent Publishers Directory",
      "email": "swp@stablebookgroup.com",
      "phone": "",
      "website": "https://shewritespress.com",
      "location": "Oakland, CA",
      "notes": "Top-tier women's hybrid publisher, 35+ titles annually, consistently ranked among top North American hybrid publishers. Single-contact model matches their author-service promise."
    },
    {
      "id": 6,
      "score": 7,
      "priority": "medium",
      "category": "Small Press (6-20 titles/yr)",
      "name": "Restless Books",
      "source": "Poets & Writers Small Presses DB",
      "email": "publisher@restlessbooks.org",
      "phone": "",
      "website": "https://restlessbooks.org",
      "location": "Amherst, MA",
      "notes": "Translated literature press, 10-15 titles annually, strong national bookstore and library presence. Precise production specs for translated fiction benefit from single-contact manufacturing."
    },
    {
      "id": 7,
      "score": 7,
      "priority": "medium",
      "category": "Small Press (6-20 titles/yr)",
      "name": "Latah Books",
      "source": "CLMP Independent Press Directory",
      "email": "editor@latahbooks.com",
      "phone": "(509) 394-4740",
      "website": "https://latahbooks.com",
      "location": "Spokane, WA",
      "notes": "Spokane indie press founded 2017, 6-10 titles annually, Ingram distribution. Growing national reach from Pacific Northwest base. Offset pricing at 500-1,000 copies outperforms current POD costs."
    },
    {
      "id": 8,
      "score": 7,
      "priority": "medium",
      "category": "Poetry & Literary Press",
      "name": "CavanKerry Press",
      "source": "Poets & Writers Small Presses DB",
      "email": "dimitri@cavankerrypress.org",
      "phone": "",
      "website": "https://cavankerrypress.org",
      "location": "Fort Lee, NJ",
      "notes": "Fort Lee NJ poetry nonprofit, 4-6 collections annually, social justice and underrepresented voices focus. Short offset poetry runs (300-750 copies) outperform POD on quality and economics."
    },
    {
      "id": 9,
      "score": 7,
      "priority": "medium",
      "category": "Small Press (6-20 titles/yr)",
      "name": "Green Writers Press",
      "source": "IBPA Member Directory",
      "email": "info@greenwriterspress.com",
      "phone": "(802) 380-1121",
      "website": "https://greenwriterspress.com",
      "location": "Brattleboro, VT",
      "notes": "Vermont environmental/sustainability press, 8-12 titles annually, strong New England bookstore distribution. Production choices signal editorial values -- single-contact guidance on paper and stock aligns with their mission."
    },
    {
      "id": 10,
      "score": 7,
      "priority": "medium",
      "category": "Poetry & Literary Press",
      "name": "Nightboat Books",
      "source": "CLMP Independent Press Directory",
      "email": "info@nightboat.org",
      "phone": "",
      "website": "https://nightboat.org",
      "location": "Brooklyn, NY",
      "notes": "Brooklyn nonprofit poetry press, 8-12 titles annually, distributed through Consortium, national literary reputation. Complex typographic specifications at short-run offset volumes demand single-contact consistency."
    },
    {
      "id": 11,
      "score": 7,
      "priority": "medium",
      "category": "Nonfiction Specialty Press",
      "name": "DoppelHouse Press",
      "source": "Reedsy Independent Publishers Directory",
      "email": "Publisher@DoppelHousePress.com",
      "phone": "(424) 258-4423",
      "website": "https://doppelhousepress.com",
      "location": "Los Angeles, CA",
      "notes": "LA art/design/illustrated nonfiction press, 6-8 titles annually. Accurate color reproduction and image fidelity require offset over digital. Single-contact spec management from quote to press check critical for illustrated titles."
    },
    {
      "id": 12,
      "score": 7,
      "priority": "medium",
      "category": "Small Press (6-20 titles/yr)",
      "name": "Unsolicited Press",
      "source": "CLMP Independent Press Directory",
      "email": "info@unsolicitedpress.com",
      "phone": "",
      "website": "https://unsolicitedpress.com",
      "location": "Portland, OR",
      "notes": "Portland indie press, 10-15 titles annually, national indie bookstore distribution. Volume pricing education (500 to 1,000 copies) helps lean press make financially sound print run decisions without in-house production expertise."
    },
    {
      "id": 13,
      "score": 7,
      "priority": "medium",
      "category": "Small Press (6-20 titles/yr)",
      "name": "Outpost19",
      "source": "Reedsy Independent Publishers Directory",
      "email": "books@outpost19.com",
      "phone": "",
      "website": "https://outpost19.com",
      "location": "San Francisco, CA",
      "notes": "San Francisco literary fiction press, 8-12 titles annually, strong editorial reputation. Offset at 500+ copies competitive vs POD with 20-day turnaround. Single-contact from estimate through delivery."
    },
    {
      "id": 14,
      "score": 7,
      "priority": "medium",
      "category": "Small Press (6-20 titles/yr)",
      "name": "Cornerstone Press",
      "source": "Poets & Writers Small Presses DB",
      "email": "cornerstone.press@uwsp.edu",
      "phone": "(715) 346-4532",
      "website": "https://cornerstonepress.uwsp.edu",
      "location": "Stevens Point, WI",
      "notes": "UW-Stevens Point student-run teaching press, 30+ titles annually, Great Lakes corridor, 6 hours from Ann Arbor. Educational manufacturing model matches teaching press mission; offset guidance extends to first-time publishers."
    },
    {
      "id": 15,
      "score": 7,
      "priority": "medium",
      "category": "Business & Authority Author",
      "name": "Nick Gray",
      "source": "LinkedIn Business Author Network",
      "email": "hello@nickgray.net",
      "phone": "",
      "website": "https://nickgray.net",
      "location": "New York, NY",
      "notes": "Self-published 'The 2-Hour Cocktail Party,' 10,000+ copies sold independently through website, events, and bulk corporate sales. Recurring print replenishment orders. Volume pricing education on 1,000-2,500 copy runs directly impacts his bulk sales margins."
    },
    {
      "id": 16,
      "score": 6,
      "priority": "medium",
      "category": "Food & Recipe Creator",
      "name": "Kylie Lato (Midwest Foodie)",
      "source": "Instagram / Food Creator Discovery",
      "email": "kylie@midwestfoodieblog.com",
      "phone": "",
      "website": "https://midwestfoodieblog.com",
      "location": "Minneapolis, MN",
      "notes": "Minnesota food blogger/creator, 100,000+ Instagram followers, published cookbook, interested in second print run. Midwest shared identity is natural outreach hook. Single-contact guidance from quote to delivery for second run upgrade."
    },
    {
      "id": 17,
      "score": 6,
      "priority": "medium",
      "category": "Small Press (6-20 titles/yr)",
      "name": "Split/Lip Press",
      "source": "CLMP Independent Press Directory",
      "email": "splitlipthepress@gmail.com",
      "phone": "",
      "website": "https://splitlippress.com",
      "location": "Chicago, IL",
      "notes": "Chicago-area flash fiction and poetry press, 8-12 titles annually, 3.5 hours from Ann Arbor. Lean operation benefits from single-contact manufacturing with reliable 20-day turnaround."
    },
    {
      "id": 18,
      "score": 6,
      "priority": "medium",
      "category": "Small Press (6-20 titles/yr)",
      "name": "Santa Fe Writers Project",
      "source": "Poets & Writers Small Presses DB",
      "email": "sfwritersproject@gmail.com",
      "phone": "",
      "website": "https://sfwp.com",
      "location": "Santa Fe, NM",
      "notes": "New Mexico literary press founded 2001, 8-12 titles annually, national reputation through award-winning catalog. Steady publication schedule; manufacturing consistency and single-contact model outweigh price shopping for quality-focused press."
    },
    {
      "id": 19,
      "score": 6,
      "priority": "medium",
      "category": "Micro Press (<=5 titles/yr)",
      "name": "Stillhouse Press",
      "source": "CLMP Independent Press Directory",
      "email": "editor@stillhousepress.org",
      "phone": "",
      "website": "https://stillhousepress.org",
      "location": "Fairfax, VA",
      "notes": "George Mason University literary press, 3-5 titles annually, Ingram distribution. Short-run offset volumes (300-750 copies) where quality and cost-efficiency align. White-glove single-contact model adds educational value for university press editorial team."
    },
    {
      "id": 20,
      "score": 6,
      "priority": "medium",
      "category": "Micro Press (<=5 titles/yr)",
      "name": "Wandering Aengus Press",
      "source": "IBPA Member Directory",
      "email": "info@trailtotable.net",
      "phone": "",
      "website": "https://wanderingaenguspress.com",
      "location": "Portland, OR",
      "notes": "Oregon micro press, 2-4 titles annually, Pacific Northwest nature writing and trail culture niche, Ingram distribution. Illustrated outdoor books require specialized paper/binding guidance. 250-copy minimum offset with single-contact spec management suits their per-title investment level."
    },
    {
      "id": 21,
      "score": 4,
      "priority": "low_supplemental",
      "category": "Food & Recipe Creator",
      "name": "Catie Gett (The Staple Store Cookbook)",
      "source": "Kickstarter Publishing Discovery",
      "email": "catie@staplestore.com.au",
      "phone": "",
      "website": "https://staplestore.com.au",
      "location": "Melbourne, VIC, AU",
      "notes": "Melbourne-based cookbook creator, Kickstarter-funded 500+ copies, explicit US distribution intent. Geographic penalty (Australia) kept score low. SUPPLEMENTAL: second run for US wholesale fulfillment eliminates cross-Pacific freight for North American market -- volume pricing story directly applicable.",
      "supplemental_justification": "US distribution intent makes a North American manufacturing partner viable for her second run. Cushing-Malloy printing 500-1,000 copies for direct US wholesale fulfillment eliminates cross-Pacific freight for her North American market. Direct personal email and active Kickstarter history confirm she is a real operator with print-volume intent."
    }
  ]
}
